django_api_engine/__init__.py
django_api_engine/apps.py
django_api_engine/version.txt
django_api_engine/admin/__init__.py
django_api_engine/api_contract/__init__.py
django_api_engine/api_contract/translation.py
django_api_engine/management/__init__.py
django_api_engine/management/commands/__init__.py
django_api_engine/migrations/__init__.py
django_api_engine/models/__init__.py
django_api_engine/signals/__init__.py
django_api_engine/tasks/__init__.py
django_api_engine/tests/__init__.py
django_api_engine/urls/__init__.py
django_api_engine/views/__init__.py
django_api_engine-0.0.17.dist-info/licenses/LICENCE
docs/screen_shots.png
django_api_engine-0.0.17.dist-info/METADATA
django_api_engine-0.0.17.dist-info/WHEEL
django_api_engine-0.0.17.dist-info/top_level.txt
django_api_engine-0.0.17.dist-info/RECORD
