Metadata-Version: 2.4
Name: django_api_engine
Version: 0.0.17
Summary: Django engine for APIs
Author-email: Lauro Cesar de Oliveira <djangoapiengine@gmail.com>
License: AGPL-3.0 license
Project-URL: Homepage, https://github.com/sharedway/django_api_engine
Project-URL: Issues, https://github.com/sharedway/django_api_engine/issues
Classifier: Environment :: Web Environment
Classifier: Framework :: Django
Requires-Python: >=3.10
License-File: LICENCE
Requires-Dist: Django>=5
Requires-Dist: djangorestframework-xml
Requires-Dist: djangorestframework
Requires-Dist: rest-pandas
Requires-Dist: requests
Requires-Dist: numpy
Requires-Dist: daphne
Requires-Dist: django-cors-headers
Requires-Dist: gunicorn
Requires-Dist: celery[auth,librabbitmq,msgpack,redis]
Requires-Dist: autobahn
Requires-Dist: Twisted[http2,tls]
Requires-Dist: channels
Requires-Dist: channels_redis
Dynamic: license-file
